xarray_tree-0.1.1.dist-info/METADATA
xarray_tree-0.1.1.dist-info/WHEEL
xarray_tree-0.1.1.dist-info/licenses/LICENSE
xarray_tree/.DS_Store
xarray_tree/__init__.py
xarray_tree/xarray_tree.py
xarray_tree-0.1.1.dist-info/RECORD
